vibeleftpad/__init__.py
vibeleftpad/ai.py
vibeleftpad/py.typed
vibeleftpad-0.1.0.dist-info/METADATA
vibeleftpad-0.1.0.dist-info/WHEEL
vibeleftpad-0.1.0.dist-info/licenses/LICENSE
vibeleftpad-0.1.0.dist-info/RECORD
