Metadata-Version: 2.4
Name: vibeleftpad
Version: 0.1.0
Summary: AI-powered left padding library that uses GPT to pad strings
Project-URL: Homepage, https://github.com/tahayparker/vibeleftpad
Project-URL: Repository, https://github.com/tahayparker/vibeleftpad
Project-URL: Issues, https://github.com/tahayparker/vibeleftpad/issues
Author-email: Taha Parker <tahayparker@gmail.com>
License: MIT
License-File: LICENSE
Keywords: ai,gpt,leftpad,padding,parody,string
Classifier: Development Status :: 3 - Alpha
Classifier: Intended Audience :: Developers
Classifier: License :: OSI Approved :: MIT License
Classifier: Programming Language :: Python :: 3
Classifier: Programming Language :: Python :: 3.10
Classifier: Programming Language :: Python :: 3.11
Classifier: Programming Language :: Python :: 3.12
Requires-Python: >=3.10
Requires-Dist: openai>=1.95.1
Requires-Dist: pydantic>=2.11.7
Requires-Dist: typing-extensions>=4.14.1
